.gitignore
LICENSE
README.md
pyproject.toml
spotrod.py
example/README.md
example/kepler_data.py
example/kepler_download.py
example/mcmc.py
example/plot.png
example/plot.py
spotrod.egg-info/PKG-INFO
spotrod.egg-info/SOURCES.txt
spotrod.egg-info/dependency_links.txt
spotrod.egg-info/requires.txt
spotrod.egg-info/top_level.txt