Metadata-Version: 2.4
Name: spotrod
Version: 3.1
Summary: A semi-analytic model for transits of spotted stars
Author-email: Bence Béky <zsebkecske@gmail.com>
License-Expression: GPL-3.0
Project-URL: Source, https://github.com/bencebeky/spotrod
Project-URL: Issues, https://github.com/bencebeky/spotrod/issues
Classifier: Intended Audience :: Science/Research
Classifier: Topic :: Scientific/Engineering :: Astronomy
Classifier: Topic :: Scientific/Engineering :: Physics
Requires-Python: >=3.9
License-File: LICENSE
Requires-Dist: numpy>=1.25.0
Dynamic: license-file
